typeable/__init__.py
typeable/_cast.py
typeable/_constraint.py
typeable/_context.py
typeable/_json.py
typeable/_object.py
typeable/typing.py
typeable-0.7.1.dist-info/licenses/LICENSE
typeable-0.7.1.dist-info/METADATA
typeable-0.7.1.dist-info/WHEEL
typeable-0.7.1.dist-info/top_level.txt
typeable-0.7.1.dist-info/zip-safe
typeable-0.7.1.dist-info/RECORD
